iktos/__init__.py
iktos/spaya/__init__.py
iktos/spaya/authorization.py
iktos/spaya/model.py
iktos/spaya/py.typed
iktos/spaya/spaya_client.py
iktos/spaya/spaya_client_async.py
iktos/spaya/spaya_client_callback.py
iktos/spaya/spaya_client_rest.py
pyspaya-1.2.0.dist-info/LICENSE
pyspaya-1.2.0.dist-info/METADATA
pyspaya-1.2.0.dist-info/WHEEL
pyspaya-1.2.0.dist-info/RECORD
