Metadata-Version: 2.1
Name: pyspaya
Version: 1.2.0
Summary: Python client for Spaya
Author: Iktos
Requires-Python: >=3.8,<4.0
Classifier: Programming Language :: Python :: 3
Classifier: Programming Language :: Python :: 3.8
Classifier: Programming Language :: Python :: 3.9
Classifier: Programming Language :: Python :: 3.10
Classifier: Programming Language :: Python :: 3.11
Classifier: Programming Language :: Python :: 3.12
Requires-Dist: pandas
Requires-Dist: requests (>=2.31.0,<3.0.0)
Requires-Dist: websockets (>=12.0,<13.0)
